ZbxAssistant/ZbxApis.py
ZbxAssistant/ZbxConfigs.py
ZbxAssistant/ZbxWxworkHosts.py
ZbxAssistant/ZbxWxworkProblems.py
ZbxAssistant/ZbxWxworkProblemsBySeverity.py
ZbxAssistant/__init__.py
zbx_wxwork_assistant-1.1.4.dist-info/METADATA
zbx_wxwork_assistant-1.1.4.dist-info/WHEEL
zbx_wxwork_assistant-1.1.4.dist-info/top_level.txt
zbx_wxwork_assistant-1.1.4.dist-info/RECORD
