Metadata-Version: 2.1
Name: zbx-wxwork-assistant
Version: 1.1.4
Summary: A simple package for zabbix-wxwork assistant tool.
Author: gary
Author-email: mepmb@sina.com
Requires-Dist: zabbix-api >=0.5.4
Requires-Dist: diskcache ~=5.4.0
